classic/domain/__init__.py
classic/domain/criteria.py
classic/domain/errors.py
classic/domain/predicate_wrapping.py
classic_domain-0.0.2.dist-info/licenses/LICENSE
classic_domain-0.0.2.dist-info/METADATA
classic_domain-0.0.2.dist-info/WHEEL
classic_domain-0.0.2.dist-info/top_level.txt
classic_domain-0.0.2.dist-info/RECORD
